Workbook

Sheet Sheet2
A3: Row Labels | B3: Sum of total_revenue | C3: Sum of unit_price
A4: Asia | B4: 159824 | C4: 45133
A5: Electronics | B5: 95021 | C5: 28912
A6: Furniture | B6: 64803 | C6: 16221
A7: Europe | B7: 163744 | C7: 48352
A8: Electronics | B8: 112050 | C8: 32728
A9: Furniture | B9: 51694 | C9: 15624
A10: Formula1 | B10: 0 | C10: 0
A11: Electronics | B11: 0 | C11: 0
A12: Furniture | B12: 0 | C12: 0
A13: USA | B13: 148495 | C13: 39501
A14: Electronics | B14: 100556 | C14: 25905
A15: Furniture | B15: 47939 | C15: 13596
A16: Grand Total | B16: 472063 | C16: 132986

Sheet Sheet5
A3: Row Labels | B3: Sum of total_revenue
A4: Asia | B4: 159824
A5: Europe | B5: 163744
A6: USA | B6: 148495
A7: Formula1 | B7: 0
A8: Grand Total | B8: 472063

Sheet Sheet6
A3: Row Labels | B3: Sum of total_revenue
A4: Chair | B4: 21243
A5: Desk | B5: 69347
A6: Headphones | B6: 16638
A7: Keyboard | B7: 7485
A8: Laptop | B8: 150407
A9: Monitor | B9: 40906
A10: Mouse | B10: 4869
A11: Phone | B11: 87322
A12: Table | B12: 73846
A13: Grand Total | B13: 472063

Sheet Sales_Data
A1: order_id | B1: order_date | C1: customer | D1: product | E1: category | F1: quantity | G1: unit_price | H1: region | I1: total_revenue | J1: Profit | K1: Price Band
A2: 3001 | B2: 2024-05-04 | C2: Nora | D2: Table | E2: Furniture | F2: 2 | G2: 373 | H2: Europe | I2: =F2*G2 -> 746 | J2: =Table1[[#This Row],[total_revenue]] * 0.25 -> 186.5 | K2: =IF(Table1[[#This Row],[unit_price]]>=500,"High",IF(Table1[[#This Row],[unit_price]]>100,"Medium","Low")) -> Medium
A3: 3002 | B3: 2024-04-16 | C3: Maria | D3: Phone | E3: Electronics | F3: 2 | G3: 469 | H3: Europe | I3: =F3*G3 -> 938 | J3: =Table1[[#This Row],[total_revenue]] * 0.25 -> 234.5 | K3: =IF(Table1[[#This Row],[unit_price]]>=500,"High",IF(Table1[[#This Row],[unit_price]]>100,"Medium","Low")) -> Medium
A4: 3003 | B4: 2024-03-08 | C4: Tom | D4: Table | E4: Furniture | F4: 2 | G4: 397 | H4: USA | I4: =F4*G4 -> 794 | J4: =Table1[[#This Row],[total_revenue]] * 0.25 -> 198.5 | K4: =IF(Table1[[#This Row],[unit_price]]>=500,"High",IF(Table1[[#This Row],[unit_price]]>100,"Medium","Low")) -> Medium
A5: 3004 | B5: 2024-05-23 | C5: Maria | D5: Keyboard | E5: Electronics | F5: 4 | G5: 22 | H5: Europe | I5: =F5*G5 -> 88 | J5: =Table1[[#This Row],[total_revenue]] * 0.25 -> 22 | K5: =IF(Table1[[#This Row],[unit_price]]>=500,"High",IF(Table1[[#This Row],[unit_price]]>100,"Medium","Low")) -> Low
A6: 3005 | B6: 2024-02-03 | C6: Noah | D6: Table | E6: Furniture | F6: 3 | G6: 391 | H6: Asia | I6: =F6*G6 -> 1173 | J6: =Table1[[#This Row],[total_revenue]] * 0.25 -> 293.25 | K6: =IF(Table1[[#This Row],[unit_price]]>=500,"High",IF(Table1[[#This Row],[unit_price]]>100,"Medium","Low")) -> Medium
A7: 3006 | B7: 2024-01-23 | C7: Elif | D7: Mouse | E7: Electronics | F7: 1 | G7: 0 | H7: USA | I7: =F7*G7 -> 0 | J7: =Table1[[#This Row],[total_revenue]] * 0.25 -> 0 | K7: =IF(Table1[[#This Row],[unit_price]]>=500,"High",IF(Table1[[#This Row],[unit_price]]>100,"Medium","Low")) -> Low
A8: 3007 | B8: 2024-04-14 | C8: Sara | D8: Phone | E8: Electronics | F8: 3 | G8: 454 | H8: USA | I8: =F8*G8 -> 1362 | J8: =Table1[[#This Row],[total_revenue]] * 0.25 -> 340.5 | K8: =IF(Table1[[#This Row],[unit_price]]>=500,"High",IF(Table1[[#This Row],[unit_price]]>100,"Medium","Low")) -> Medium
A9: 3008 | B9: 2024-06-10 | C9: Omar | D9: Phone | E9: Electronics | F9: 1 | G9: 409 | H9: Asia | I9: =F9*G9 -> 409 | J9: =Table1[[#This Row],[total_revenue]] * 0.25 -> 102.25 | K9: =IF(Table1[[#This Row],[unit_price]]>=500,"High",IF(Table1[[#This Row],[unit_price]]>100,"Medium","Low")) -> Medium
A10: 3009 | B10: 2024-03-03 | C10: Omar | D10: Keyboard | E10: Electronics | F10: 3 | G10: 49 | H10: Europe | I10: =F10*G10 -> 147 | J10: =Table1[[#This Row],[total_revenue]] * 0.25 -> 36.75 | K10: =IF(Table1[[#This Row],[unit_price]]>=500,"High",IF(Table1[[#This Row],[unit_price]]>100,"Medium","Low")) -> Low
A11: 3010 | B11: 2024-03-10 | C11: Lina | D11: Chair | E11: Furniture | F11: 6 | G11: 60 | H11: Asia | I11: =F11*G11 -> 360 | J11: =Table1[[#This Row],[total_revenue]] * 0.25 -> 90 | K11: =IF(Table1[[#This Row],[unit_price]]>=500,"High",IF(Table1[[#This Row],[unit_price]]>100,"Medium","Low")) -> Low
A12: 3011 | B12: 2024-05-21 | C12: Maria | D12: Monitor | E12: Electronics | F12: 6 | G12: 157 | H12: Asia | I12: =F12*G12 -> 942 | J12: =Table1[[#This Row],[total_revenue]] * 0.25 -> 235.5 | K12: =IF(Table1[[#This Row],[unit_price]]>=500,"High",IF(Table1[[#This Row],[unit_price]]>100,"Medium","Low")) -> Medium
A13: 3012 | B13: 2024-03-28 | C13: Omar | D13: Phone | E13: Electronics | F13: 4 | G13: 444 | H13: Asia | I13: =F13*G13 -> 1776 | J13: =Table1[[#This Row],[total_revenue]] * 0.25 -> 444 | K13: =IF(Table1[[#This Row],[unit_price]]>=500,"High",IF(Table1[[#This Row],[unit_price]]>100,"Medium","Low")) -> Medium
... A501: 3500 | B501: 2024-01-04 | C501: Noah | D501: Desk | E501: Furniture | F501: 3 | G501: 275 | H501: USA | I501: =F501*G501 -> 825 | J501: =Table1[[#This Row],[total_revenue]] * 0.25 -> 206.25 | K501: =IF(Table1[[#This Row],[unit_price]]>=500,"High",IF(Table1[[#This Row],[unit_price]]>100,"Medium","Low")) -> Medium

Sheet Sheet3
A1: Product | B1: Standard_price | C1: Ctegory_std | D1: Standard Price | E1: Price Check
A2: Laptop | B2: 900 | C2: Electronics | D2: {=Sales_Data!L1S} -> #NAME?
A3: Phone | B3: 450 | C3: Electronics | D3: {=Sales_Data!L1S} -> #NAME?
A4: Mouse | B4: 25 | C4: Electronics | D4: {=Sales_Data!L1S} -> #NAME?
A5: Keyboard | B5: 35 | C5: Electronics | D5: {=Sales_Data!L1S} -> #NAME?
A6: Monitor | B6: 200 | C6: Electronics | D6: {=Sales_Data!L1S} -> #NAME?
A7: Headphones | B7: 75 | C7: Electronics | D7: {=Sales_Data!L1S} -> #NAME?
A8: Desk | B8: 300 | C8: Furniture | D8: {=Sales_Data!L1S} -> #NAME?
A9: Chair | B9: 100 | C9: Furniture | D9: {=Sales_Data!L1S} -> #NAME?
A10: Table | B10: 350 | C10: Furniture | D10: {=Sales_Data!L1S} -> #NAME?

Sheet Sheet1
E4: Summary
D6: Total company revenue | F6: =SUM(Table1[total_revenue]) -> 472063
D7: Average order value | F7: =AVERAGE(Table1[total_revenue]) -> 944.126
D8: Highest order | F8: =MAX(Table1[total_revenue]) -> 5670
D9: Lowest order | F9: =MIN(Table1[total_revenue]) -> -126
D10: Total Revenue of Electronics | F10: =SUMIF(Table1[category],"Electronics",Table1[total_revenue]) -> 307627
D11: Revenue For Europe + electronics | F11: =SUMIFS(Table1[total_revenue],Table1[region],"Europe",Table1[category],"Electronics") -> 112050
D12: How many orders from Asia | F12: =COUNTIF(Table1[region],"Asia") -> 166
D13: Average unit price for Furniture | F13: =AVERAGEIF(Table1[category],"Furniture",Table1[unit_price]) -> 258.1875
